CHANGES.txt
LICENSE.txt
MANIFEST.in
README.txt
cgi2scgi.c
pyproject.toml
setup.py
apache2/Makefile
apache2/README.txt
apache2/mod_scgi.c
doc/CHANGES_110.txt
doc/LICENSE_110.txt
doc/guide.html
doc/protocol.txt
scgi/__init__.py
scgi/passfd.c
scgi/quixote_handler.py
scgi/scgi_server.py
scgi/session_server.py
scgi/systemd_socket.py
scgi/test_passfd.py
scgi/util.py
scgi.egg-info/PKG-INFO
scgi.egg-info/SOURCES.txt
scgi.egg-info/dependency_links.txt
scgi.egg-info/top_level.txt