Metadata-Version: 1.2
Name: scgi
Version: 2.2
Summary: A Python package for implementing SCGI servers.
Home-page: http://python.ca/scgi/
Author: Neil Schemenauer
Author-email: nas@arctrix.com
License: DFSG approved (see LICENSE.txt)
Download-URL: http://python.ca/scgi/releases/scgi-2.2.tar.gz
Platform: UNKNOWN
Classifier: Development Status :: 5 - Production/Stable
Classifier: Environment :: Web Environment
Classifier: License :: DFSG approved
Classifier: Intended Audience :: Developers
Classifier: Operating System :: Unix
Classifier: Operating System :: Microsoft :: Windows
Classifier: Operating System :: MacOS :: MacOS X
Classifier: Topic :: Internet :: WWW/HTTP :: Dynamic Content
Classifier: Programming Language :: Python :: 3 :: Only
Requires-Python: >=3.5
